cached_url/__init__.py
cached_url-0.0.39.dist-info/LICENSE
cached_url-0.0.39.dist-info/METADATA
cached_url-0.0.39.dist-info/WHEEL
cached_url-0.0.39.dist-info/top_level.txt
cached_url-0.0.39.dist-info/RECORD
