Metadata-Version: 2.1
Name: cached-url
Version: 0.0.39
Summary: Library for get url content (cached when testing).
Home-page: https://github.com/gaoyunzhi/cached_url
Author: Yunzhi Gao
Author-email: gaoyunzhi@gmail.com
License: UNKNOWN
Platform: UNKNOWN
Classifier: Programming Language :: Python :: 3
Classifier: License :: OSI Approved :: MIT License
Classifier: Operating System :: OS Independent
Requires-Python: >=3.0
License-File: LICENSE
